asu/__init__.py
asu/api.py
asu/asu.py
asu/branches.yml
asu/build.py
asu/common.py
asu/janitor.py
asu/metrics.py
asu/openapi.yml
asu/static/logo.png
asu/static/style.css
asu/templates/overview.html
asu-0.7.20.dist-info/LICENSE
asu-0.7.20.dist-info/METADATA
asu-0.7.20.dist-info/WHEEL
asu-0.7.20.dist-info/RECORD
