Metadata-Version: 2.1
Name: asu
Version: 0.7.20
Summary: An image on demand server for OpenWrt based distributions
License: GPL-2.0
Author: Paul Spooren
Author-email: mail@aparcar.org
Requires-Python: >=3.8,<4.0
Classifier: License :: OSI Approved :: GNU General Public License v2 (GPLv2)
Classifier: Programming Language :: Python :: 3
Classifier: Programming Language :: Python :: 3.8
Classifier: Programming Language :: Python :: 3.9
Classifier: Programming Language :: Python :: 3.10
Classifier: Programming Language :: Python :: 3.11
Requires-Dist: PyNaCl (>=1.5.0,<2.0.0)
Requires-Dist: connexion[swagger-ui] (>=2.14.2,<3.0.0)
Requires-Dist: gunicorn (>=20.1.0,<21.0.0)
Requires-Dist: prometheus-client (>=0.13.1,<0.14.0)
Requires-Dist: redis (>=4.5.1,<5.0.0)
Requires-Dist: requests (>=2.28.2,<3.0.0)
Requires-Dist: rq (>=1.13.0,<2.0.0)
